{
    "id": "org.kde.kbruch",
    "runtime": "org.kde.Platform",
    "runtime-version": "5.15",
    "sdk": "org.kde.Sdk",
    "command": "kbruch",
    "rename-icon": "kbruch",
    "finish-args": [
        "--share=ipc",
        "--socket=x11",
        "--socket=wayland",
        "--device=dri"
    ],
    "modules": [
        {
            "name": "kbruch",
            "buildsystem": "cmake-ninja",
            "sources": [ 
                { 
                    "type": "archive", 
                    "url": "https://download.kde.org/stable/release-service/21.04.3/src/kbruch-21.04.3.tar.xz",
                    "sha256": "947bc5eed80aa35c63275d9f23728c684acc0a7d4f5cc2ff94b7de39b12435bb"
                } 
            ]        
        }
    ]
}
